python_sonycisip2/__init__.py
python_sonycisip2/commandset.py
python_sonycisip2/python_sonycisip2.py
python_sonycisip2/variables.py
python_sonycisip2-0.2.5.dist-info/LICENSE
python_sonycisip2-0.2.5.dist-info/METADATA
python_sonycisip2-0.2.5.dist-info/WHEEL
python_sonycisip2-0.2.5.dist-info/top_level.txt
python_sonycisip2-0.2.5.dist-info/RECORD
